pyspur/__init__.py
pyspur/database.py
pyspur/workflow_builder.py
pyspur/workflow_code_handler.py
pyspur/api/__init__.py
pyspur/api/ai_management.py
pyspur/api/api_app.py
pyspur/api/dataset_management.py
pyspur/api/evals_management.py
pyspur/api/file_management.py
pyspur/api/key_management.py
pyspur/api/main.py
pyspur/api/node_management.py
pyspur/api/openai_compatible_api.py
pyspur/api/output_file_management.py
pyspur/api/rag_management.py
pyspur/api/run_management.py
pyspur/api/session_management.py
pyspur/api/template_management.py
pyspur/api/user_management.py
pyspur/api/workflow_code_convert.py
pyspur/api/workflow_management.py
pyspur/api/workflow_run.py
pyspur/cli/__init__.py
pyspur/cli/main.py
pyspur/cli/utils.py
pyspur/dataset/ds_util.py
pyspur/evals/README.MD
pyspur/evals/common.py
pyspur/evals/evaluator.py
pyspur/evals/tasks/gpqa.py
pyspur/evals/tasks/gpqa.yaml
pyspur/evals/tasks/gsm8k.yaml
pyspur/evals/tasks/math.yaml
pyspur/evals/tasks/mmlu.yaml
pyspur/examples/tool_function_example.py
pyspur/examples/workflow_as_code_example.py
pyspur/execution/__init__.py
pyspur/execution/task_recorder.py
pyspur/execution/workflow_execution_context.py
pyspur/execution/workflow_executor.py
pyspur/integrations/google/auth.py
pyspur/integrations/google/client.py
pyspur/integrations/slack/client.py
pyspur/models/base_model.py
pyspur/models/dataset_model.py
pyspur/models/dc_and_vi_model.py
pyspur/models/eval_run_model.py
pyspur/models/output_file_model.py
pyspur/models/run_model.py
pyspur/models/task_model.py
pyspur/models/user_session_model.py
pyspur/models/workflow_model.py
pyspur/models/workflow_version_model.py
pyspur/models/management/alembic/README
pyspur/models/management/alembic/env.py
pyspur/models/management/alembic/script.py.mako
pyspur/models/management/alembic/versions/000_init_db.py
pyspur/models/management/alembic/versions/001_fix_workflow_version_idx.py
pyspur/models/management/alembic/versions/002_add_knowledge_base_model.py
pyspur-0.1.18.dist-info/METADATA
pyspur-0.1.18.dist-info/WHEEL
pyspur-0.1.18.dist-info/entry_points.txt
pyspur-0.1.18.dist-info/RECORD
