Metadata-Version: 2.4
Name: pyspur
Version: 0.1.18
Summary: PySpur is a Graph UI for building AI Agents in Python
Project-URL: Repository, https://github.com/pyspur-dev/pyspur
Project-URL: Documentation, https://docs.pyspur.dev
Maintainer-email: Srijan Patel <srijan@pyspur.dev>, Jean Kaddour <jean@pyspur.dev>, Parshva Bhadra <parshva.bhadra@pyspur.dev>
License-Expression: Apache-2.0
Classifier: Development Status :: 4 - Beta
Classifier: Intended Audience :: Developers
Classifier: Operating System :: MacOS :: MacOS X
Classifier: Operating System :: POSIX :: Linux
Classifier: Operating System :: Unix
Classifier: Programming Language :: Python :: 3.11
Classifier: Programming Language :: Python :: 3.12
Requires-Python: >=3.11
Requires-Dist: alembic==1.14.0
Requires-Dist: arrow==1.3.0
Requires-Dist: asyncio==3.4.3
Requires-Dist: attrs==24.3.0
Requires-Dist: backend==0.2.4.1
Requires-Dist: chromadb==0.6.2
Requires-Dist: datasets==3.2.0
Requires-Dist: docx2python==3.3.0
Requires-Dist: docx2txt==0.8
Requires-Dist: exa-py==1.9.0
Requires-Dist: fastapi==0.115.6
Requires-Dist: firecrawl-py==1.10.2
Requires-Dist: genanki==0.13.1
Requires-Dist: google-api-python-client==2.159.0
Requires-Dist: grpcio==1.69.0
Requires-Dist: httpx[http2]==0.27.2
Requires-Dist: itsdangerous==2.2.0
Requires-Dist: jinja2==3.1.6
Requires-Dist: litellm==1.61.15
Requires-Dist: loguru==0.7.3
Requires-Dist: numpy==2.2.1
Requires-Dist: ollama==0.4.5
Requires-Dist: pandas==2.2.3
Requires-Dist: phidata==2.7.8
Requires-Dist: pinecone==5.4.2
Requires-Dist: praw==7.8.1
Requires-Dist: psycopg2-binary==2.9.10
Requires-Dist: py-zerox==0.0.7
Requires-Dist: pydantic==2.10.5
Requires-Dist: pygithub==2.5.0
Requires-Dist: pypdf==5.1.0
Requires-Dist: python-dotenv==1.0.1
Requires-Dist: python-multipart==0.0.20
Requires-Dist: python-pptx==1.0.2
Requires-Dist: pyyaml==6.0.2
Requires-Dist: qdrant-client==1.12.2
Requires-Dist: redis==5.2.1
Requires-Dist: regex==2024.11.6
Requires-Dist: requests-file==2.1.0
Requires-Dist: requests-oauthlib==1.3.1
Requires-Dist: requests==2.32.3
Requires-Dist: resend==2.6.0
Requires-Dist: retrying==1.3.4
Requires-Dist: sendgrid==6.11.0
Requires-Dist: six==1.17.0
Requires-Dist: slack-sdk==3.34.0
Requires-Dist: sqlalchemy==2.0.36
Requires-Dist: supabase==2.11.0
Requires-Dist: tenacity==8.3.0
Requires-Dist: tiktoken==0.7.0
Requires-Dist: tqdm==4.67.1
Requires-Dist: typer[all]==0.9.0
Requires-Dist: weaviate-client==4.10.2
Requires-Dist: youtube-transcript-api==0.6.3
Provides-Extra: dev
Requires-Dist: pytest-cov>=4.0; extra == 'dev'
Requires-Dist: pytest>=7.0; extra == 'dev'
Requires-Dist: ruff>=0.1.0; extra == 'dev'
